{
  "timestamp": "2025-07-31T19:12:26.102085",
  "current_page": 2,
  "processed_urls": [
    "https://www.work.ua/resumes/9752676/?puid=41",
    "https://www.work.ua/resumes/14770627/",
    "https://www.work.ua/resumes/13913812/?puid=5282",
    "https://www.work.ua/resumes/13828297/",
    "https://www.work.ua/resumes/14770555/",
    "https://www.work.ua/resumes/14388679/",
    "https://www.work.ua/resumes/4201550/",
    "https://www.work.ua/resumes/3590356/",
    "https://www.work.ua/resumes/936821/?puid=41",
    "https://www.work.ua/resumes/7381338/?puid=41",
    "https://www.work.ua/resumes/894244/",
    "https://www.work.ua/resumes/14770660/",
    "https://www.work.ua/resumes/14257576/",
    "https://www.work.ua/resumes/2981210/",
    "https://www.work.ua/resumes/5215073/",
    "https://www.work.ua/resumes/14770618/?puid=41",
    "https://www.work.ua/resumes/14567803/",
    "https://www.work.ua/resumes/14770471/",
    "https://www.work.ua/resumes/5123507/",
    "https://www.work.ua/resumes/11856096/?puid=41",
    "https://www.work.ua/resumes/5776952/?puid=41",
    "https://www.work.ua/resumes/14770537/",
    "https://www.work.ua/resumes/294897/",
    "https://www.work.ua/resumes/14770615/",
    "https://www.work.ua/resumes/5262337/",
    "https://www.work.ua/resumes/9535668/?puid=41",
    "https://www.work.ua/resumes/14770636/",
    "https://www.work.ua/resumes/14585812/"
  ],
  "failed_urls": [],
  "successful_resumes": 28,
  "driver_restarts": 3,
  "data_file": "resume_data_20250731_190906.json"
}